wihmt/__init__.py
wihmt/__main__.py
wihmt/py.typed
wihmt/server.py
wihmt-0.1.0.dist-info/entry_points.txt
wihmt-0.1.0.dist-info/LICENSE.rst
wihmt-0.1.0.dist-info/WHEEL
wihmt-0.1.0.dist-info/METADATA
wihmt-0.1.0.dist-info/RECORD
