Metadata-Version: 2.1
Name: wihmt
Version: 0.1.0
Summary: Will I have money tomorrow
Home-page: https://github.com/asteroide/wihmt
License: MIT
Author: Asteroide
Author-email: asteroide@domtombox.net
Requires-Python: >=3.8,<4.0
Classifier: License :: OSI Approved :: MIT License
Classifier: Programming Language :: Python :: 3
Classifier: Programming Language :: Python :: 3.7
Classifier: Programming Language :: Python :: 3.8
Classifier: Programming Language :: Python :: 3.9
Requires-Dist: click (>=7.0,<8.0)
Requires-Dist: dash (>=1.19.0,<2.0.0)
Requires-Dist: ofxtools (>=0.9.1,<0.10.0)
Requires-Dist: pandas (>=1.2.1,<2.0.0)
Project-URL: Changelog, https://github.com/asteroide/wihmt/releases
Project-URL: Documentation, https://wihmt.readthedocs.io
Project-URL: Repository, https://github.com/asteroide/wihmt
